game/__init__.py
game/ui_1.jpg
game/ui_2.jpg
game/web.py
game/static/base.js
game/static/browserfs.min.js
game/static/es6-promise.min.js
game/static/favicon.ico
game/static/game.html
game/static/jquery.min.js
game/static/loader.js
game/static/mamenes.js
game/static/mamenes_wasm.js
game/static/mamenes_wasm.wasm
game-0.0.5.dist-info/LICENSE
game-0.0.5.dist-info/METADATA
game-0.0.5.dist-info/WHEEL
game-0.0.5.dist-info/entry_points.txt
game-0.0.5.dist-info/top_level.txt
game-0.0.5.dist-info/RECORD
